gendit/__init__.py
gendit/_duckdb.py
gendit/api.py
gendit/core.py
gendit-1.0.0a2.dist-info/LICENSE
gendit-1.0.0a2.dist-info/METADATA
gendit-1.0.0a2.dist-info/WHEEL
gendit-1.0.0a2.dist-info/RECORD
