Metadata-Version: 2.1
Name: gendit
Version: 1.0.0a2
Summary: simple large scale data generator
License: MIT
Author: Fabien Arcellier
Author-email: fabien.arcellier@gmail.com
Requires-Python: >=3.10,<4.0
Classifier: Intended Audience :: Developers
Classifier: License :: OSI Approved :: MIT License
Classifier: Operating System :: OS Independent
Classifier: Programming Language :: Python :: 3
Classifier: Programming Language :: Python :: 3.10
Classifier: Programming Language :: Python :: 3.11
Classifier: Programming Language :: Python :: 3.12
Requires-Dist: duckdb (>=1.0.0,<2.0.0)
Requires-Dist: pyarrow (>=16.1.0,<17.0.0)
Requires-Dist: tqdm (>=4.66.4,<5.0.0)
